iv_tools
