Metadata-Version: 1.1
Name: iv-tools
Version: 0.0.3
Summary: IV Tools
Home-page: UNKNOWN
Author: varun
Author-email: varunsrikanth91@gmail.com
License: UNKNOWN
Keywords: python
Platform: UNKNOWN
Classifier: Development Status :: 1 - Planning
Classifier: Intended Audience :: Developers
Classifier: Programming Language :: Python :: 3
Classifier: Operating System :: Unix
Classifier: Operating System :: MacOS :: MacOS X
Classifier: Operating System :: Microsoft :: Windows
